LICENSE
MANIFEST.in
README.md
requirements.txt
setup.py
gpt_linter/__init__.py
gpt_linter/__main__.py
gpt_linter/common.py
gpt_linter/gptlinter.py
gpt_linter/guide.py
gpt_linter/linter.py
gpt_linter/logger.py
gpt_linter/singleton.py
gpt_linter.egg-info/PKG-INFO
gpt_linter.egg-info/SOURCES.txt
gpt_linter.egg-info/dependency_links.txt
gpt_linter.egg-info/requires.txt
gpt_linter.egg-info/top_level.txt